CHANGELOG.txt
LICENCE.txt
MANIFEST.in
README.txt
setup.py
ankit_discounts_calculator.egg-info/PKG-INFO
ankit_discounts_calculator.egg-info/SOURCES.txt
ankit_discounts_calculator.egg-info/dependency_links.txt
ankit_discounts_calculator.egg-info/top_level.txt
discount_calculator/__init__.py
discount_calculator/discount_calculator.py