Metadata-Version: 2.1
Name: ankit-discounts-calculator
Version: 0.0.1
Summary: A very basic discount calculator
Home-page: 
Author: Ankit Kumar
Author-email: x22113886@student.ncirl.ie
License: MIT
Keywords: discount calculator
Classifier: Development Status :: 5 - Production/Stable
Classifier: Intended Audience :: Education
Classifier: Operating System :: MacOS
Classifier: License :: OSI Approved :: MIT License
Classifier: Programming Language :: Python :: 3.8
License-File: LICENCE.txt
